qwerky_vllm_models/__init__.py
qwerky_vllm_models/configuration.py
qwerky_vllm_models/modeling.py
qwerky_vllm_models-0.2.41.dist-info/METADATA
qwerky_vllm_models-0.2.41.dist-info/WHEEL
qwerky_vllm_models-0.2.41.dist-info/entry_points.txt
qwerky_vllm_models-0.2.41.dist-info/top_level.txt
qwerky_vllm_models-0.2.41.dist-info/RECORD
