Metadata-Version: 2.4
Name: qwerky-vllm-models
Version: 0.2.41
Summary: vLLM plugin for Qwerky AI MambaInLlama hybrid models
Author-email: Qwerky AI <contact@qwerky.ai>
License: Apache-2.0
Project-URL: Homepage, https://github.com/qwerkyai/qwerky-vllm-models
Project-URL: Repository, https://github.com/qwerkyai/qwerky-vllm-models
Classifier: Development Status :: 4 - Beta
Classifier: Intended Audience :: Developers
Classifier: License :: OSI Approved :: Apache Software License
Classifier: Programming Language :: Python :: 3
Classifier: Programming Language :: Python :: 3.10
Classifier: Programming Language :: Python :: 3.11
Classifier: Programming Language :: Python :: 3.12
Classifier: Topic :: Scientific/Engineering :: Artificial Intelligence
Requires-Python: >=3.10
Requires-Dist: torch>=2.0.0
Requires-Dist: transformers>=4.40.0
Requires-Dist: vllm>=0.14.0
Requires-Dist: einops>=0.7.0
Provides-Extra: dev
Requires-Dist: pytest>=7.0.0; extra == "dev"
Requires-Dist: pytest-asyncio>=0.21.0; extra == "dev"
